{
  "station": [
    {
      "id": "1",
      "name": "Lesson 1",
      "streamURL": "https://drive.google.com/uc?export=download&id=1f9txLtuBRKGokZftwn6A7DgtxzpBQaj9",
      "imageURL": "",
      "desc": "",
      "longDesc": "Fast - Speak Kirundi Language"
    },
    {
      "id": "2",
      "name": "Lesson 2",
      "streamURL": "https://drive.google.com/uc?export=download&id=1-GN4zktRqnzPBvJe1lmJyx5nbWK7jICz",
      "imageURL": "",
      "desc": "",
      "longDesc": "Fast - Speak Kirundi Language"
    },
    {
      "id": "3",
      "name": "Lesson 3",
      "streamURL": "https://drive.google.com/uc?export=download&id=13_eAKFTE7sAvThxvzjQnlBZoAueldAXY",
      "imageURL": "",
      "desc": "",
      "longDesc": "Fast - Speak Kirundi Language"
    },
    {
      "id": "4",
      "name": "Lesson 4",
      "streamURL": "https://drive.google.com/uc?export=download&id=1e-xL_H0P2Pxu88aYBLreDQXS6Wy728dv",
      "imageURL": "",
      "desc": "",
      "longDesc": "Fast - Speak Kirundi Language"
    },
    {
      "id": "5",
      "name": "Lesson 5",
      "streamURL": "https://drive.google.com/uc?export=download&id=1QdkQ-f5p4MJA6IHoJn3pW0_InrBjZmxs",
      "imageURL": "",
      "desc": "",
      "longDesc": "Fast - Speak Kirundi Language"
    },
    {
      "id": "6",
      "name": "Lesson 6",
      "streamURL": "https://drive.google.com/uc?export=download&id=1TDZ5WivatMX1X5bPAA-TU1q9pO1cFqM9",
      "imageURL": "",
      "desc": "",
      "longDesc": "Fast - Speak Kirundi Language"
    },
    {
      "id": "7",
      "name": "Lesson 7",
      "streamURL": "https://drive.google.com/uc?export=download&id=1-2cWTbdkjUuDS1IDlnJzwx_MobFrDMf-",
      "imageURL": "",
      "desc": "",
      "longDesc": "Fast - Speak Kirundi Language"
    },
    {
      "id": "8",
      "name": "Lesson 8",
      "streamURL": "https://drive.google.com/uc?export=download&id=1khgBhmGIPyRAJBrTEv8aao-iSFv_S6Kp",
      "imageURL": "",
      "desc": "",
      "longDesc": "Fast - Speak Kirundi Language"
    },
    {
      "id": "9",
      "name": "Lesson 9",
      "streamURL": "https://drive.google.com/uc?export=download&id=1pTsPDcSrR4wDTw791uodNlwF2lqz63y1",
      "imageURL": "",
      "desc": "",
      "longDesc": "Fast - Speak Kirundi Language"
    },
    {
      "id": "10",
      "name": "Lesson 10",
      "streamURL": "https://drive.google.com/uc?export=download&id=1RgfWHXb6N1NDN2bjQk9_ClMhlGqgw2VZ",
      "imageURL": "",
      "desc": "",
      "longDesc": "Fast - Speak Kirundi Language"
    },
    {
      "id": "11",
      "name": "Lesson 11",
      "streamURL": "https://drive.google.com/uc?export=download&id=1Zjx7b4ZI37v5Yer1l6qJDxNc8lAFPO51",
      "imageURL": "",
      "desc": "",
      "longDesc": "Fast - Speak Kirundi Language"
    },
    {
      "id": "12",
      "name": "Lesson 12",
      "streamURL": "https://drive.google.com/uc?export=download&id=1PHqOBmLxGO1EWXdu9YA1PMw98vUfLFNP",
      "imageURL": "",
      "desc": "",
      "longDesc": "Fast - Speak Kirundi Language"
    },
    {
      "id": "13",
      "name": "Lesson 13",
      "streamURL": "https://drive.google.com/uc?export=download&id=1ZJYfnD8ASatjbRqpagwhh7Wpxh52CIxq",
      "imageURL": "",
      "desc": "",
      "longDesc": "Fast - Speak Kirundi Language"
    },
    {
      "id": "14",
      "name": "Lesson 14",
      "streamURL": "https://drive.google.com/uc?export=download&id=11oes1oBmy0pnKLAnHWZ_vNhV-Wkm7rza",
      "imageURL": "",
      "desc": "",
      "longDesc": "Fast - Speak Kirundi Language"
    },
    {
      "id": "15",
      "name": "Lesson 15",
      "streamURL": "https://drive.google.com/uc?export=download&id=1Kwipl1RldGH4tRfLGIjVy8i0krmexGeG",
      "imageURL": "",
      "desc": "",
      "longDesc": "Fast - Speak Kirundi Language"
    },
    {
      "id": "16",
      "name": "Lesson 16",
      "streamURL": "https://drive.google.com/uc?export=download&id=1BKATiiLEcLWi03noGmTbsUmoLhvIYBcw",
      "imageURL": "",
      "desc": "",
      "longDesc": "Fast - Speak Kirundi Language"
    },
    {
      "id": "17",
      "name": "Lesson 17",
      "streamURL": "https://drive.google.com/uc?export=download&id=1VyI5YLTATAg1yJHOpPmcSmO7PzzKJZRC",
      "imageURL": "",
      "desc": "",
      "longDesc": "Fast - Speak Kirundi Language"
    },
    {
      "id": "18",
      "name": "Lesson 18",
      "streamURL": "https://drive.google.com/uc?export=download&id=12Ha0BM5pehWsj88SUYdYtZPD6YIayfNz",
      "imageURL": "",
      "desc": "",
      "longDesc": "Fast - Speak Kirundi Language"
    },
    {
      "id": "19",
      "name": "Lesson 19",
      "streamURL": "https://drive.google.com/uc?export=download&id=1G43ighjHTyJgnqaH0EhQu9nrCz3jpeZ0",
      "imageURL": "",
      "desc": "",
      "longDesc": "Fast - Speak Kirundi Language"
    },
    {
      "id": "20",
      "name": "Lesson 20",
      "streamURL": "https://drive.google.com/uc?export=download&id=1Xm0HFuAMgWfcQjUzZ9SPepQzpo8F_4Mu",
      "imageURL": "",
      "desc": "",
      "longDesc": "Fast - Speak Kirundi Language"
    },
    {
      "id": "21",
      "name": "Lesson 21",
      "streamURL": "https://drive.google.com/uc?export=download&id=13v0aXh_ODPYyqmSTJdwKz3LkkV0flpbw",
      "imageURL": "",
      "desc": "",
      "longDesc": "Fast - Speak Kirundi Language"
    },
    {
      "id": "22",
      "name": "Lesson 22",
      "streamURL": "https://drive.google.com/uc?export=download&id=1zZLAuokkaD6w3ev6CDRDNQUeDXMazqDQ",
      "imageURL": "",
      "desc": "",
      "longDesc": "Fast - Speak Kirundi Language"
    },
    {
      "id": "23",
      "name": "Lesson 23",
      "streamURL": "https://drive.google.com/uc?export=download&id=11ShpIadGCnvK7WcIzIa6_21tIILDEnqr",
      "imageURL": "",
      "desc": "",
      "longDesc": "Fast - Speak Kirundi Language"
    },
    {
      "id": "24",
      "name": "Lesson 24",
      "streamURL": "https://drive.google.com/uc?export=download&id=1Gu_tkErm1r1kmCj5QI_oQ4b09StVZRU2",
      "imageURL": "",
      "desc": "",
      "longDesc": "Fast - Speak Kirundi Language"
    },
    {
      "id": "25",
      "name": "Lesson 25",
      "streamURL": "https://drive.google.com/uc?export=download&id=1njSPt54IpjvbZ7hYXVauyaVGti54Ku2_",
      "imageURL": "",
      "desc": "",
      "longDesc": "Fast - Speak Kirundi Language"
    },
    {
      "id": "26",
      "name": "Lesson 26",
      "streamURL": "https://drive.google.com/uc?export=download&id=1kjFtwkWJhjbMfdA1srALQnjv9SQvXlZ3",
      "imageURL": "",
      "desc": "",
      "longDesc": "Fast - Speak Kirundi Language"
    },
    {
      "id": "27",
      "name": "Lesson 27",
      "streamURL": "https://drive.google.com/uc?export=download&id=1rvxzoTG-H0Cmfy6CE0DbJotRIGh4yJeh",
      "imageURL": "",
      "desc": "",
      "longDesc": "Fast - Speak Kirundi Language"
    },
    {
      "id": "28",
      "name": "Lesson 28",
      "streamURL": "https://drive.google.com/uc?export=download&id=11S5ZyZYCJROPIB-UuSbpsI472l7tEmk1",
      "imageURL": "",
      "desc": "",
      "longDesc": "Fast - Speak Kirundi Language"
    },
    {
      "id": "29",
      "name": "Lesson 29",
      "streamURL": "https://drive.google.com/uc?export=download&id=1kUVXREfu-odmhsyXwpAmkp-lYiwBGl-g",
      "imageURL": "",
      "desc": "",
      "longDesc": "Fast - Speak Kirundi Language"
    },
    {
      "id": "30",
      "name": "Lesson 30",
      "streamURL": "https://drive.google.com/uc?export=download&id=1Ve3wn-OVQ7UDIUm3O2IooiINsBq-gW2m",
      "imageURL": "",
      "desc": "",
      "longDesc": "Fast - Speak Kirundi Language"
    },
    {
      "id": "31",
      "name": "Lesson 31",
      "streamURL": "https://drive.google.com/uc?export=download&id=18wvIrEU9rMMXFbfi4sIHlLhGHV73haSL",
      "imageURL": "",
      "desc": "",
      "longDesc": "Fast - Speak Kirundi Language"
    },
    {
      "id": "32",
      "name": "Lesson 32",
      "streamURL": "https://drive.google.com/uc?export=download&id=1MkOcPzFFyUwhaAqt38wsOaApNrWlqC-y",
      "imageURL": "",
      "desc": "",
      "longDesc": "Fast - Speak Kirundi Language"
    },
    {
      "id": "33",
      "name": "Lesson 33",
      "streamURL": "https://drive.google.com/uc?export=download&id=1KYIJr-_TbrhMt2EVSL5hslZky-9N3_lN",
      "imageURL": "",
      "desc": "",
      "longDesc": "Fast - Speak Kirundi Language"
    },
    {
      "id": "34",
      "name": "Lesson 34",
      "streamURL": "https://drive.google.com/uc?export=download&id=1yWFF3ZgcxRQgDwUHjQdhBP8OWSJ5-fFY",
      "imageURL": "",
      "desc": "",
      "longDesc": "Fast - Speak Kirundi Language"
    },
    {
      "id": "35",
      "name": "Lesson 35",
      "streamURL": "https://drive.google.com/uc?export=download&id=1P72DbiNTkB94AopP7gg8pziaMfDy4vIF",
      "imageURL": "",
      "desc": "",
      "longDesc": "Fast - Speak Kirundi Language"
    }
  ]
}
